naturalexperiments/__init__.py
naturalexperiments/benchmark.py
naturalexperiments/data_summary.py
naturalexperiments/model.py
naturalexperiments/utils.py
naturalexperiments/data/__init__.py
naturalexperiments/data/acic/__init__.py
naturalexperiments/data/ihdp/__init__.py
naturalexperiments/data/jobs/__init__.py
naturalexperiments/data/news/__init__.py
naturalexperiments/data/rorco/__init__.py
naturalexperiments/data/rorco/metadata_generate.py
naturalexperiments/data/rorco/rorco_preprocess.py
naturalexperiments/data/twins/__init__.py
naturalexperiments/estimators/__init__.py
naturalexperiments/estimators/catenet.py
naturalexperiments/estimators/causalforest.py
naturalexperiments/estimators/direct_difference.py
naturalexperiments/estimators/direct_prediction.py
naturalexperiments/estimators/double_double.py
naturalexperiments/estimators/doubly_robust.py
naturalexperiments/estimators/horvitz_thompson.py
naturalexperiments/estimators/learned_direct.py
naturalexperiments/estimators/off_policy.py
naturalexperiments/estimators/propensity_stratification.py
naturalexperiments/estimators/regression_discontinuity.py
naturalexperiments/estimators/tmle.py
naturalexperiments-0.2.3.dist-info/LICENSE
naturalexperiments-0.2.3.dist-info/METADATA
naturalexperiments-0.2.3.dist-info/WHEEL
naturalexperiments-0.2.3.dist-info/top_level.txt
naturalexperiments-0.2.3.dist-info/RECORD
