Metadata-Version: 2.1
Name: naturalexperiments
Version: 0.2.3
Summary: Estimators and datasets for treatment effect estimation in natural experiments.
Home-page: https://github.com/rtealwitter/naturalexperiments
Author: R. Teal Witter
Author-email: rtealwitter@gmail.com
Classifier: Programming Language :: Python :: 3
Classifier: License :: OSI Approved :: MIT License
Classifier: Operating System :: OS Independent
Requires-Python: >=3.6
License-File: LICENSE
Requires-Dist: torch
Requires-Dist: numpy
Requires-Dist: pandas
Requires-Dist: scikit-learn
Requires-Dist: scipy
Requires-Dist: matplotlib
Requires-Dist: geopandas
Requires-Dist: geopy
Requires-Dist: contextily
Requires-Dist: tqdm
Requires-Dist: catenets
Requires-Dist: tabulate
Requires-Dist: rdata
